nic_parser/__init__.py
nic_parser/parser.py
nic_parser-0.2.0.dist-info/LICENSE
nic_parser-0.2.0.dist-info/METADATA
nic_parser-0.2.0.dist-info/WHEEL
nic_parser-0.2.0.dist-info/top_level.txt
nic_parser-0.2.0.dist-info/RECORD
