Metadata-Version: 2.1
Name: nic-parser
Version: 0.2.0
Summary: A python library to parse Sri Lankan national identity card numbers
Home-page: https://github.com/chehanr/nic_parser
Author: Chehan Ratnasiri
Author-email: chehan.rat@gmail.com
License: GNU General Public License
Download-URL: https://github.com/chehanr/nic_parser/archive/0.1.0.tar.gz
Keywords: nic,parser,sri-lanka
Platform: UNKNOWN
